decision_tree/__init__.py
decision_tree_typed-0.1.0.dist-info/LICENSE.txt
decision_tree_typed-0.1.0.dist-info/METADATA
decision_tree_typed-0.1.0.dist-info/WHEEL
decision_tree_typed-0.1.0.dist-info/top_level.txt
decision_tree_typed-0.1.0.dist-info/RECORD
