Metadata-Version: 2.1
Name: decision-tree-typed
Version: 0.1.0
Summary: A statically typed python decision tree module
Home-page: https://github.com/mxmeinhold/decision-tree
Author: Max Meinhold
Author-email: mxmeinhold@gmail.com
License: MIT
Project-URL: Bug Tracker, https://github.com/mxmeinhold/decision-tree/issues
Keywords: decision-tree machine-learning
Platform: UNKNOWN
Classifier: Programming Language :: Python :: 3
Classifier: Programming Language :: Python :: 3.10
Classifier: License :: OSI Approved :: MIT License
Classifier: Operating System :: OS Independent
Classifier: Natural Language :: English
Classifier: Intended Audience :: Developers
Classifier: Topic :: Scientific/Engineering :: Artificial Intelligence
Classifier: Typing :: Typed
Requires-Python: >=3.10
